[
	{
		"key": "dbln",
		"value": "%7B%2261590819535170%22%3A%22TDL4MiIl%22%7D",
		"domain": "facebook.com",
		"path": "/login/device-based/",
		"hostOnly": false,
		"creation": "2026-06-12T16:51:29.971Z",
		"lastAccessed": "2026-06-12T16:51:29.972Z"
	},
	{
		"key": "sb",
		"value": "OS0iav3iVuEq4_mEI4NFMK_Y",
		"domain": "facebook.com",
		"path": "/",
		"hostOnly": false,
		"creation": "2026-06-12T16:51:29.972Z",
		"lastAccessed": "2026-06-12T16:51:29.972Z"
	},
	{
		"key": "datr",
		"value": "OS0iakM2H9k1eUMtcPGqqR1W",
		"domain": "facebook.com",
		"path": "/",
		"hostOnly": false,
		"creation": "2026-06-12T16:51:29.973Z",
		"lastAccessed": "2026-06-12T16:51:29.973Z"
	},
	{
		"key": "ps_l",
		"value": "1",
		"domain": "facebook.com",
		"path": "/",
		"hostOnly": false,
		"creation": "2026-06-12T16:51:29.973Z",
		"lastAccessed": "2026-06-12T16:51:29.973Z"
	},
	{
		"key": "ps_n",
		"value": "1",
		"domain": "facebook.com",
		"path": "/",
		"hostOnly": false,
		"creation": "2026-06-12T16:51:29.973Z",
		"lastAccessed": "2026-06-12T16:51:29.973Z"
	},
	{
		"key": "locale",
		"value": "ar_AR",
		"domain": "facebook.com",
		"path": "/",
		"hostOnly": false,
		"creation": "2026-06-12T16:51:29.973Z",
		"lastAccessed": "2026-06-12T16:51:29.973Z"
	},
	{
		"key": "wd",
		"value": "1280x689",
		"domain": "facebook.com",
		"path": "/",
		"hostOnly": false,
		"creation": "2026-06-12T16:51:29.973Z",
		"lastAccessed": "2026-06-12T16:51:29.973Z"
	},
	{
		"key": "oo",
		"value": "v1",
		"domain": "facebook.com",
		"path": "/",
		"hostOnly": false,
		"creation": "2026-06-12T16:51:29.973Z",
		"lastAccessed": "2026-06-12T16:51:29.973Z"
	},
	{
		"key": "c_user",
		"value": "100094978907051",
		"domain": "facebook.com",
		"path": "/",
		"hostOnly": false,
		"creation": "2026-06-12T16:51:29.973Z",
		"lastAccessed": "2026-06-12T16:51:29.973Z"
	},
	{
		"key": "fr",
		"value": "1Pvr53gpmaJ3aCpTn.AWdjn7Ykb9YM4I88gNInvNmxeVz4mrKW3eXAjjyNpYtp5a9F4RU.BqLEPI..AAA.0.0.BqLEPI.AWcVR312YFfbX9Cr6kf5QHQURrk",
		"domain": "facebook.com",
		"path": "/",
		"hostOnly": false,
		"creation": "2026-06-12T16:51:29.973Z",
		"lastAccessed": "2026-06-12T16:51:29.973Z"
	},
	{
		"key": "xs",
		"value": "23%3An1TJRy8pESg3Cg%3A2%3A1781285822%3A-1%3A-1%3A%3AAcxR_oZ0SmlyJ7_aa4-xY6TscAxOT_CG3HCKxXdDJw",
		"domain": "facebook.com",
		"path": "/",
		"hostOnly": false,
		"creation": "2026-06-12T16:51:29.973Z",
		"lastAccessed": "2026-06-12T16:51:29.973Z"
	},
	{
		"key": "presence",
		"value": "C%7B%22lm3%22%3A%22g.899092766515073%22%2C%22t3%22%3A%5B%7B%22o%22%3A0%2C%22i%22%3A%22g.2212800262816711%22%7D%5D%2C%22utc3%22%3A1781282443022%2C%22v%22%3A1%7D",
		"domain": "facebook.com",
		"path": "/",
		"hostOnly": false,
		"creation": "2026-06-12T16:51:29.973Z",
		"lastAccessed": "2026-06-12T16:51:29.973Z"
	}
]
